snusbase/__init__.py
snusbase/snus.py
snusbase-0.1.0.dist-info/METADATA
snusbase-0.1.0.dist-info/WHEEL
snusbase-0.1.0.dist-info/top_level.txt
snusbase-0.1.0.dist-info/RECORD
