Metadata-Version: 2.1
Name: snusbase
Version: 0.1.0
Summary: API Wrapper for Snusbase
Author: leon
Author-email: viiiee@femboy.cx
Requires-Dist: httpx
